hello_issac/cli.py
hello_issac-1.0.0.dist-info/DESCRIPTION.rst
hello_issac-1.0.0.dist-info/METADATA
hello_issac-1.0.0.dist-info/RECORD
hello_issac-1.0.0.dist-info/WHEEL
hello_issac-1.0.0.dist-info/entry_points.txt
hello_issac-1.0.0.dist-info/metadata.json
hello_issac-1.0.0.dist-info/top_level.txt
