Metadata-Version: 2.0
Name: hello-issac
Version: 1.0.0
Summary: A Python package to print hello issac
Home-page: https://github.com/mandiladitya
Author: Aditya Mandil
Author-email: adityamandil317@gmail.com
License: MIT
Platform: UNKNOWN
Classifier: License :: OSI Approved :: MIT License
Classifier: Programming Language :: Python :: 3
Classifier: Programming Language :: Python :: 3.7
Requires-Dist: requests
